photogrammetry_photos_pipeline/__init__.py
photogrammetry_photos_pipeline/dehaze/__init__.py
photogrammetry_photos_pipeline/dehaze/he_2009.py
photogrammetry_photos_pipeline/dehaze/meng_2013_x.py
photogrammetry_photos_pipeline/dehaze/meng_2013/__init__.py
photogrammetry_photos_pipeline/dehaze/meng_2013/air_light.py
photogrammetry_photos_pipeline/dehaze/meng_2013/bon_con.py
photogrammetry_photos_pipeline/dehaze/meng_2013/cal_transmission.py
photogrammetry_photos_pipeline/exif/__init__.py
photogrammetry_photos_pipeline/scripts/__init__.py
photogrammetry_photos_pipeline/scripts/pipeline.py
photogrammetry_photos_pipeline-0.1.3.dist-info/METADATA
photogrammetry_photos_pipeline-0.1.3.dist-info/WHEEL
photogrammetry_photos_pipeline-0.1.3.dist-info/entry_points.txt
photogrammetry_photos_pipeline-0.1.3.dist-info/top_level.txt
photogrammetry_photos_pipeline-0.1.3.dist-info/RECORD
