Metadata-Version: 2.1
Name: photogrammetry-photos-pipeline
Version: 0.1.3
Summary: Prepare photos for a photogrammetry assembly
Home-page: https://github.com/terra-submersa/photogrammetry-photos-pipeline
Author: Alexandre Masselot
Author-email: alexandre.masselot@gmail.com
Project-URL: Bug Tracker, https://github.com/terra-submersa/photogrammetry-photos-pipeline/issues
Classifier: Programming Language :: Python :: 3
Classifier: License :: OSI Approved :: MIT License
Classifier: Operating System :: OS Independent
Requires-Python: >=3.9
Requires-Dist: coordinates-label-photos
Requires-Dist: tqdm (==4.64.0)
Requires-Dist: numpy (==1.23.2)
Requires-Dist: piexif (==1.1.3)
